CHANGES.txt
LICENSE.txt
MANIFEST.in
README.rst
requirements.txt
setup.py
summary/__init__.py
summary/filters.py
summary/techniques.py
summary/url.py
summary_extraction.egg-info/.DS_Store
summary_extraction.egg-info/PKG-INFO
summary_extraction.egg-info/SOURCES.txt
summary_extraction.egg-info/dependency_links.txt
summary_extraction.egg-info/requires.txt
summary_extraction.egg-info/top_level.txt