Metadata-Version: 1.0
Name: summary-extraction
Version: 0.2
Summary: Extract the title, image and description from any URL.
Home-page: https://github.com/svven/summary
Author: Alexandru Stanciu
Author-email: alexandru.stanciu@gmail.com
License: LICENSE.txt
Platform: UNKNOWN
